grpc_feature_client/__init__.py
grpc_feature_client/client.py
grpc_feature_client/config.py
grpc_feature_client/grpc_codegen.py
grpc_feature_client-1.0.1.dist-info/METADATA
grpc_feature_client-1.0.1.dist-info/WHEEL
grpc_feature_client-1.0.1.dist-info/RECORD
