Metadata-Version: 2.4
Name: grpc_feature_client
Version: 1.0.1
Summary: High-performance gRPC client for BharatML Stack real-time feature operations
Project-URL: Homepage, https://github.com/Meesho/BharatMLStack
Project-URL: Bug Tracker, https://github.com/Meesho/BharatMLStack/issues
Project-URL: Source, https://github.com/Meesho/BharatMLStack/tree/main/py-sdk/grpc_feature_client
Author-email: Jaya Kommuru <jaya.kommuru@meesho.com>, BharatML Stack Team <bharatml@meesho.com>
License: BharatMLStack Business Source License 1.1
Classifier: License :: Other/Proprietary License
Classifier: Operating System :: OS Independent
Classifier: Programming Language :: Python :: 3
Requires-Python: >=3.7
Requires-Dist: bharatml-commons>=1.0.1
Requires-Dist: grpcio-tools>=1.50.0
Requires-Dist: grpcio>=1.50.0
Provides-Extra: dev
Requires-Dist: black; extra == 'dev'
Requires-Dist: flake8; extra == 'dev'
Requires-Dist: isort; extra == 'dev'
Requires-Dist: mypy; extra == 'dev'
Requires-Dist: pytest>=6.0; extra == 'dev'
